<?xml version="1.0" encoding="UTF-8"?>
<objects serializationModel="Studio.02.02.00">
	<object class="AudioFile" id="{f8d400c9-4f81-4408-9c52-77e95155e3a9}">
		<property name="assetPath">
			<value>mi.mp3</value>
		</property>
		<property name="frequencyInKHz">
			<value>44.0999985</value>
		</property>
		<property name="channelCount">
			<value>2</value>
		</property>
		<property name="length">
			<value>3.5004081632653059</value>
		</property>
		<relationship name="masterAssetFolder">
			<destination>{42516543-e291-409a-be65-ecb8adf46757}</destination>
		</relationship>
	</object>
</objects>
